{
	"animations": [
		{
			"loop": false,
			"offsets": [
				0,
				0
			],
			"anim": "idle",
			"fps": 24,
			"name": "freddy idle",
			"indices": []
		},
		{
			"loop": false,
			"offsets": [
				0,
				0
			],
			"anim": "singDOWN",
			"fps": 24,
			"name": "freddy down",
			"indices": []
		},
		{
			"loop": false,
			"offsets": [
				0,
				0
			],
			"anim": "singUP",
			"fps": 24,
			"name": "freddy up",
			"indices": []
		},
		{
			"loop": false,
			"offsets": [
				0,
				0
			],
			"anim": "singLEFT",
			"fps": 24,
			"name": "freddy left",
			"indices": []
		},
		{
			"loop": false,
			"offsets": [
				0,
				0
			],
			"anim": "singRIGHT",
			"fps": 24,
			"name": "freddy right",
			"indices": []
		}
	],
	"no_antialiasing": false,
	"image": "characters/freddy",
	"position": [
		-210,
		-370
	],
	"healthicon": "help",
	"flip_x": false,
	"healthbar_colors": [
		255,
		0,
		0
	],
	"camera_position": [
		200,
		-340
	],
	"sing_duration": 6.1,
	"scale": 1.05
}